digitalbrainsdk/__init__.py
digitalbrainsdk/config.ini
digitalbrainsdk/core.py
digitalbrainsdk/utils.py
digitalbrainsdk/api/__init__.py
digitalbrainsdk/api/api_module.py
digitalbrainsdk/api/analyze/__init__.py
digitalbrainsdk/api/analyze/analyze_api.py
digitalbrainsdk/api/analyze/projection_api.py
digitalbrainsdk/api/api/__init__.py
digitalbrainsdk/api/api/core.py
digitalbrainsdk/api/queries/__init__.py
digitalbrainsdk/api/queries/region_api.py
digitalbrainsdk/api/queries/swc_api.py
digitalbrainsdk/config/__init__.py
digitalbrainsdk/config/config.py
digitalbrainsdk/tests/__init__.py
digitalbrainsdk/tests/test_analyze.py
digitalbrainsdk/tests/test_core.py
digitalbrainsdk/tests/test_projection.py
digitalbrainsdk/tests/test_region.py
digitalbrainsdk/tests/test_swc_api.py
digitalbrainsdk/utils/__init__.py
digitalbrainsdk/visualization/__init__.py
digitalbrainsdk/visualization/swc_visualization.py
digitalbrainsdk-0.0.9.dist-info/METADATA
digitalbrainsdk-0.0.9.dist-info/WHEEL
digitalbrainsdk-0.0.9.dist-info/top_level.txt
digitalbrainsdk-0.0.9.dist-info/RECORD
