Metadata-Version: 2.1
Name: digitalbrainsdk
Version: 0.0.9
Summary: A Python SDK for Digital Brain analysis
Home-page: 
Author: XingLi
Author-email: lihouxing@yeah.net
Classifier: Programming Language :: Python :: 3
Classifier: License :: OSI Approved :: MIT License
Classifier: Operating System :: OS Independent
Requires-Python: >=3.6
Requires-Dist: asttokens==3.0.0
Requires-Dist: backports.tarfile==1.2.0
Requires-Dist: certifi==2024.12.14
Requires-Dist: charset-normalizer==3.4.1
Requires-Dist: colorama==0.4.6
Requires-Dist: comm==0.2.2
Requires-Dist: contourpy==1.3.1
Requires-Dist: cycler==0.12.1
Requires-Dist: decorator==5.1.1
Requires-Dist: docutils==0.21.2
Requires-Dist: executing==2.1.0
Requires-Dist: fonttools==4.55.3
Requires-Dist: freetype-py==2.5.1
Requires-Dist: glfw==2.8.0
Requires-Dist: glob2==0.7
Requires-Dist: graphviz==0.20.3
Requires-Dist: hsluv==5.0.4
Requires-Dist: idna==3.10
Requires-Dist: importlib-metadata==8.5.0
Requires-Dist: ipython==8.31.0
Requires-Dist: ipywidgets==8.1.5
Requires-Dist: jaraco.classes==3.4.0
Requires-Dist: jaraco.context==6.0.1
Requires-Dist: jaraco.functools==4.1.0
Requires-Dist: jedi==0.19.2
Requires-Dist: joblib==1.4.2
Requires-Dist: jupyter-rfb==0.4.4
Requires-Dist: jupyterlab-widgets==3.0.13
Requires-Dist: kaleido==0.2.1
Requires-Dist: keyring==25.6.0
Requires-Dist: kiwisolver==1.4.8
Requires-Dist: markdown-it-py==3.0.0
Requires-Dist: matplotlib==3.10.0
Requires-Dist: matplotlib-inline==0.1.7
Requires-Dist: mdurl==0.1.2
Requires-Dist: more-itertools==10.5.0
Requires-Dist: nh3==0.2.20
Requires-Dist: numpy==1.26.4
Requires-Dist: packaging==24.2
Requires-Dist: pandas==2.2.3
Requires-Dist: parso==0.8.4
Requires-Dist: pillow==11.1.0
Requires-Dist: pkginfo==1.12.0
Requires-Dist: prompt-toolkit==3.0.48
Requires-Dist: pure-eval==0.2.3
Requires-Dist: Pygments==2.18.0
Requires-Dist: pynrrd==1.1.1
Requires-Dist: pyparsing==3.2.1
Requires-Dist: pyswcloader==1.1.1
Requires-Dist: python-dateutil==2.9.0.post0
Requires-Dist: pytz==2024.2
Requires-Dist: pywin32-ctypes==0.2.3
Requires-Dist: rdp==0.8
Requires-Dist: readme-renderer==44.0
Requires-Dist: requests==2.32.3
Requires-Dist: requests-toolbelt==1.0.0
Requires-Dist: rfc3986==2.0.0
Requires-Dist: rich==13.9.4
Requires-Dist: scikit-learn==1.6.0
Requires-Dist: scipy==1.14.1
Requires-Dist: seaborn==0.13.2
Requires-Dist: six==1.17.0
Requires-Dist: stack-data==0.6.3
Requires-Dist: statistics==1.0.3.5
Requires-Dist: threadpoolctl==3.5.0
Requires-Dist: tqdm==4.67.1
Requires-Dist: traitlets==5.14.3
Requires-Dist: treelib==1.7.0
Requires-Dist: twine==6.0.1
Requires-Dist: typing-extensions==4.12.2
Requires-Dist: tzdata==2024.2
Requires-Dist: urllib3==2.3.0
Requires-Dist: vispy==0.14.3
Requires-Dist: wcwidth==0.2.13
Requires-Dist: widgetsnbextension==4.0.13
Requires-Dist: zipp==3.21.0
